{"name":"gleam","counts":{"deprecated":0,"unstable":0,"stable":0,"unmarked":3773},"submodules":[{"name":"gl","counts":{"deprecated":0,"unstable":0,"stable":0,"unmarked":3772},"submodules":[{"name":"Accum","counts":{"deprecated":0,"unstable":0,"stable":0,"unmarked":3},"submodules":[]},{"name":"ActiveTexture","counts":{"deprecated":0,"unstable":0,"stable":0,"unmarked":3},"submodules":[]},{"name":"AlphaFunc","counts":{"deprecated":0,"unstable":0,"stable":0,"unmarked":3},"submodules":[]},{"name":"AreTexturesResident","counts":{"deprecated":0,"unstable":0,"stable":0,"unmarked":3},"submodules":[]},{"name":"ArrayElement","counts":{"deprecated":0,"unstable":0,"stable":0,"unmarked":3},"submodules":[]},{"name":"AttachShader","counts":{"deprecated":0,"unstable":0,"stable":0,"unmarked":3},"submodules":[]},{"name":"Begin","counts":{"deprecated":0,"unstable":0,"stable":0,"unmarked":3},"submodules":[]},{"name":"BeginConditionalRender","counts":{"deprecated":0,"unstable":0,"stable":0,"unmarked":3},"submodules":[]},{"name":"BeginQuery","counts":{"deprecated":0,"unstable":0,"stable":0,"unmarked":3},"submodules":[]},{"name":"BeginTransformFeedback","counts":{"deprecated":0,"unstable":0,"stable":0,"unmarked":3},"submodules":[]},{"name":"BindAttribLocation","counts":{"deprecated":0,"unstable":0,"stable":0,"unmarked":3},"submodules":[]},{"name":"BindBuffer","counts":{"deprecated":0,"unstable":0,"stable":0,"unmarked":3},"submodules":[]},{"name":"BindBufferBase","counts":{"deprecated":0,"unstable":0,"stable":0,"unmarked":3},"submodules":[]},{"name":"BindBufferRange","counts":{"deprecated":0,"unstable":0,"stable":0,"unmarked":3},"submodules":[]},{"name":"BindFragDataLocation","counts":{"deprecated":0,"unstable":0,"stable":0,"unmarked":3},"submodules":[]},{"name":"BindFramebuffer","counts":{"deprecated":0,"unstable":0,"stable":0,"unmarked":3},"submodules":[]},{"name":"BindRenderbuffer","counts":{"deprecated":0,"unstable":0,"stable":0,"unmarked":3},"submodules":[]},{"name":"BindTexture","counts":{"deprecated":0,"unstable":0,"stable":0,"unmarked":3},"submodules":[]},{"name":"BindVertexArray","counts":{"deprecated":0,"unstable":0,"stable":0,"unmarked":3},"submodules":[]},{"name":"Bitmap","counts":{"deprecated":0,"unstable":0,"stable":0,"unmarked":3},"submodules":[]},{"name":"BlendColor","counts":{"deprecated":0,"unstable":0,"stable":0,"unmarked":3},"submodules":[]},{"name":"BlendEquation","counts":{"deprecated":0,"unstable":0,"stable":0,"unmarked":3},"submodules":[]},{"name":"BlendEquationSeparate","counts":{"deprecated":0,"unstable":0,"stable":0,"unmarked":3},"submodules":[]},{"name":"BlendFunc","counts":{"deprecated":0,"unstable":0,"stable":0,"unmarked":3},"submodules":[]},{"name":"BlendFuncSeparate","counts":{"deprecated":0,"unstable":0,"stable":0,"unmarked":3},"submodules":[]},{"name":"BlitFramebuffer","counts":{"deprecated":0,"unstable":0,"stable":0,"unmarked":3},"submodules":[]},{"name":"BufferData","counts":{"deprecated":0,"unstable":0,"stable":0,"unmarked":3},"submodules":[]},{"name":"BufferSubData","counts":{"deprecated":0,"unstable":0,"stable":0,"unmarked":3},"submodules":[]},{"name":"CallList","counts":{"deprecated":0,"unstable":0,"stable":0,"unmarked":3},"submodules":[]},{"name":"CallLists","counts":{"deprecated":0,"unstable":0,"stable":0,"unmarked":3},"submodules":[]},{"name":"CheckFramebufferStatus","counts":{"deprecated":0,"unstable":0,"stable":0,"unmarked":3},"submodules":[]},{"name":"ClampColor","counts":{"deprecated":0,"unstable":0,"stable":0,"unmarked":3},"submodules":[]},{"name":"Clear","counts":{"deprecated":0,"unstable":0,"stable":0,"unmarked":3},"submodules":[]},{"name":"ClearAccum","counts":{"deprecated":0,"unstable":0,"stable":0,"unmarked":3},"submodules":[]},{"name":"ClearBufferfi","counts":{"deprecated":0,"unstable":0,"stable":0,"unmarked":3},"submodules":[]},{"name":"ClearBufferfv","counts":{"deprecated":0,"unstable":0,"stable":0,"unmarked":3},"submodules":[]},{"name":"ClearBufferiv","counts":{"deprecated":0,"unstable":0,"stable":0,"unmarked":3},"submodules":[]},{"name":"ClearBufferuiv","counts":{"deprecated":0,"unstable":0,"stable":0,"unmarked":3},"submodules":[]},{"name":"ClearColor","counts":{"deprecated":0,"unstable":0,"stable":0,"unmarked":3},"submodules":[]},{"name":"ClearDepth","counts":{"deprecated":0,"unstable":0,"stable":0,"unmarked":3},"submodules":[]},{"name":"ClearIndex","counts":{"deprecated":0,"unstable":0,"stable":0,"unmarked":3},"submodules":[]},{"name":"ClearStencil","counts":{"deprecated":0,"unstable":0,"stable":0,"unmarked":3},"submodules":[]},{"name":"ClientActiveTexture","counts":{"deprecated":0,"unstable":0,"stable":0,"unmarked":3},"submodules":[]},{"name":"ClipPlane","counts":{"deprecated":0,"unstable":0,"stable":0,"unmarked":3},"submodules":[]},{"name":"Color3b","counts":{"deprecated":0,"unstable":0,"stable":0,"unmarked":3},"submodules":[]},{"name":"Color3bv","counts":{"deprecated":0,"unstable":0,"stable":0,"unmarked":3},"submodules":[]},{"name":"Color3d","counts":{"deprecated":0,"unstable":0,"stable":0,"unmarked":3},"submodules":[]},{"name":"Color3dv","counts":{"deprecated":0,"unstable":0,"stable":0,"unmarked":3},"submodules":[]},{"name":"Color3f","counts":{"deprecated":0,"unstable":0,"stable":0,"unmarked":3},"submodules":[]},{"name":"Color3fv","counts":{"deprecated":0,"unstable":0,"stable":0,"unmarked":3},"submodules":[]},{"name":"Color3i","counts":{"deprecated":0,"unstable":0,"stable":0,"unmarked":3},"submodules":[]},{"name":"Color3iv","counts":{"deprecated":0,"unstable":0,"stable":0,"unmarked":3},"submodules":[]},{"name":"Color3s","counts":{"deprecated":0,"unstable":0,"stable":0,"unmarked":3},"submodules":[]},{"name":"Color3sv","counts":{"deprecated":0,"unstable":0,"stable":0,"unmarked":3},"submodules":[]},{"name":"Color3ub","counts":{"deprecated":0,"unstable":0,"stable":0,"unmarked":3},"submodules":[]},{"name":"Color3ubv","counts":{"deprecated":0,"unstable":0,"stable":0,"unmarked":3},"submodules":[]},{"name":"Color3ui","counts":{"deprecated":0,"unstable":0,"stable":0,"unmarked":3},"submodules":[]},{"name":"Color3uiv","counts":{"deprecated":0,"unstable":0,"stable":0,"unmarked":3},"submodules":[]},{"name":"Color3us","counts":{"deprecated":0,"unstable":0,"stable":0,"unmarked":3},"submodules":[]},{"name":"Color3usv","counts":{"deprecated":0,"unstable":0,"stable":0,"unmarked":3},"submodules":[]},{"name":"Color4b","counts":{"deprecated":0,"unstable":0,"stable":0,"unmarked":3},"submodules":[]},{"name":"Color4bv","counts":{"deprecated":0,"unstable":0,"stable":0,"unmarked":3},"submodules":[]},{"name":"Color4d","counts":{"deprecated":0,"unstable":0,"stable":0,"unmarked":3},"submodules":[]},{"name":"Color4dv","counts":{"deprecated":0,"unstable":0,"stable":0,"unmarked":3},"submodules":[]},{"name":"Color4f","counts":{"deprecated":0,"unstable":0,"stable":0,"unmarked":3},"submodules":[]},{"name":"Color4fv","counts":{"deprecated":0,"unstable":0,"stable":0,"unmarked":3},"submodules":[]},{"name":"Color4i","counts":{"deprecated":0,"unstable":0,"stable":0,"unmarked":3},"submodules":[]},{"name":"Color4iv","counts":{"deprecated":0,"unstable":0,"stable":0,"unmarked":3},"submodules":[]},{"name":"Color4s","counts":{"deprecated":0,"unstable":0,"stable":0,"unmarked":3},"submodules":[]},{"name":"Color4sv","counts":{"deprecated":0,"unstable":0,"stable":0,"unmarked":3},"submodules":[]},{"name":"Color4ub","counts":{"deprecated":0,"unstable":0,"stable":0,"unmarked":3},"submodules":[]},{"name":"Color4ubv","counts":{"deprecated":0,"unstable":0,"stable":0,"unmarked":3},"submodules":[]},{"name":"Color4ui","counts":{"deprecated":0,"unstable":0,"stable":0,"unmarked":3},"submodules":[]},{"name":"Color4uiv","counts":{"deprecated":0,"unstable":0,"stable":0,"unmarked":3},"submodules":[]},{"name":"Color4us","counts":{"deprecated":0,"unstable":0,"stable":0,"unmarked":3},"submodules":[]},{"name":"Color4usv","counts":{"deprecated":0,"unstable":0,"stable":0,"unmarked":3},"submodules":[]},{"name":"ColorMask","counts":{"deprecated":0,"unstable":0,"stable":0,"unmarked":3},"submodules":[]},{"name":"ColorMaski","counts":{"deprecated":0,"unstable":0,"stable":0,"unmarked":3},"submodules":[]},{"name":"ColorMaterial","counts":{"deprecated":0,"unstable":0,"stable":0,"unmarked":3},"submodules":[]},{"name":"ColorPointer","counts":{"deprecated":0,"unstable":0,"stable":0,"unmarked":3},"submodules":[]},{"name":"CompileShader","counts":{"deprecated":0,"unstable":0,"stable":0,"unmarked":3},"submodules":[]},{"name":"CompressedTexImage1D","counts":{"deprecated":0,"unstable":0,"stable":0,"unmarked":3},"submodules":[]},{"name":"CompressedTexImage2D","counts":{"deprecated":0,"unstable":0,"stable":0,"unmarked":3},"submodules":[]},{"name":"CompressedTexImage3D","counts":{"deprecated":0,"unstable":0,"stable":0,"unmarked":3},"submodules":[]},{"name":"CompressedTexSubImage1D","counts":{"deprecated":0,"unstable":0,"stable":0,"unmarked":3},"submodules":[]},{"name":"CompressedTexSubImage2D","counts":{"deprecated":0,"unstable":0,"stable":0,"unmarked":3},"submodules":[]},{"name":"CompressedTexSubImage3D","counts":{"deprecated":0,"unstable":0,"stable":0,"unmarked":3},"submodules":[]},{"name":"CopyPixels","counts":{"deprecated":0,"unstable":0,"stable":0,"unmarked":3},"submodules":[]},{"name":"CopyTexImage1D","counts":{"deprecated":0,"unstable":0,"stable":0,"unmarked":3},"submodules":[]},{"name":"CopyTexImage2D","counts":{"deprecated":0,"unstable":0,"stable":0,"unmarked":3},"submodules":[]},{"name":"CopyTexSubImage1D","counts":{"deprecated":0,"unstable":0,"stable":0,"unmarked":3},"submodules":[]},{"name":"CopyTexSubImage2D","counts":{"deprecated":0,"unstable":0,"stable":0,"unmarked":3},"submodules":[]},{"name":"CopyTexSubImage3D","counts":{"deprecated":0,"unstable":0,"stable":0,"unmarked":3},"submodules":[]},{"name":"CreateProgram","counts":{"deprecated":0,"unstable":0,"stable":0,"unmarked":3},"submodules":[]},{"name":"CreateShader","counts":{"deprecated":0,"unstable":0,"stable":0,"unmarked":3},"submodules":[]},{"name":"CullFace","counts":{"deprecated":0,"unstable":0,"stable":0,"unmarked":3},"submodules":[]},{"name":"DeleteBuffers","counts":{"deprecated":0,"unstable":0,"stable":0,"unmarked":3},"submodules":[]},{"name":"DeleteFramebuffers","counts":{"deprecated":0,"unstable":0,"stable":0,"unmarked":3},"submodules":[]},{"name":"DeleteLists","counts":{"deprecated":0,"unstable":0,"stable":0,"unmarked":3},"submodules":[]},{"name":"DeleteProgram","counts":{"deprecated":0,"unstable":0,"stable":0,"unmarked":3},"submodules":[]},{"name":"DeleteQueries","counts":{"deprecated":0,"unstable":0,"stable":0,"unmarked":3},"submodules":[]},{"name":"DeleteRenderbuffers","counts":{"deprecated":0,"unstable":0,"stable":0,"unmarked":3},"submodules":[]},{"name":"DeleteShader","counts":{"deprecated":0,"unstable":0,"stable":0,"unmarked":3},"submodules":[]},{"name":"DeleteTextures","counts":{"deprecated":0,"unstable":0,"stable":0,"unmarked":3},"submodules":[]},{"name":"DeleteVertexArrays","counts":{"deprecated":0,"unstable":0,"stable":0,"unmarked":3},"submodules":[]},{"name":"DepthFunc","counts":{"deprecated":0,"unstable":0,"stable":0,"unmarked":3},"submodules":[]},{"name":"DepthMask","counts":{"deprecated":0,"unstable":0,"stable":0,"unmarked":3},"submodules":[]},{"name":"DepthRange","counts":{"deprecated":0,"unstable":0,"stable":0,"unmarked":3},"submodules":[]},{"name":"DetachShader","counts":{"deprecated":0,"unstable":0,"stable":0,"unmarked":3},"submodules":[]},{"name":"Disable","counts":{"deprecated":0,"unstable":0,"stable":0,"unmarked":3},"submodules":[]},{"name":"DisableClientState","counts":{"deprecated":0,"unstable":0,"stable":0,"unmarked":3},"submodules":[]},{"name":"DisableVertexAttribArray","counts":{"deprecated":0,"unstable":0,"stable":0,"unmarked":3},"submodules":[]},{"name":"Disablei","counts":{"deprecated":0,"unstable":0,"stable":0,"unmarked":3},"submodules":[]},{"name":"DrawArrays","counts":{"deprecated":0,"unstable":0,"stable":0,"unmarked":3},"submodules":[]},{"name":"DrawBuffer","counts":{"deprecated":0,"unstable":0,"stable":0,"unmarked":3},"submodules":[]},{"name":"DrawBuffers","counts":{"deprecated":0,"unstable":0,"stable":0,"unmarked":3},"submodules":[]},{"name":"DrawElements","counts":{"deprecated":0,"unstable":0,"stable":0,"unmarked":3},"submodules":[]},{"name":"DrawPixels","counts":{"deprecated":0,"unstable":0,"stable":0,"unmarked":3},"submodules":[]},{"name":"DrawRangeElements","counts":{"deprecated":0,"unstable":0,"stable":0,"unmarked":3},"submodules":[]},{"name":"EdgeFlag","counts":{"deprecated":0,"unstable":0,"stable":0,"unmarked":3},"submodules":[]},{"name":"EdgeFlagPointer","counts":{"deprecated":0,"unstable":0,"stable":0,"unmarked":3},"submodules":[]},{"name":"EdgeFlagv","counts":{"deprecated":0,"unstable":0,"stable":0,"unmarked":3},"submodules":[]},{"name":"Enable","counts":{"deprecated":0,"unstable":0,"stable":0,"unmarked":3},"submodules":[]},{"name":"EnableClientState","counts":{"deprecated":0,"unstable":0,"stable":0,"unmarked":3},"submodules":[]},{"name":"EnableVertexAttribArray","counts":{"deprecated":0,"unstable":0,"stable":0,"unmarked":3},"submodules":[]},{"name":"Enablei","counts":{"deprecated":0,"unstable":0,"stable":0,"unmarked":3},"submodules":[]},{"name":"End","counts":{"deprecated":0,"unstable":0,"stable":0,"unmarked":3},"submodules":[]},{"name":"EndConditionalRender","counts":{"deprecated":0,"unstable":0,"stable":0,"unmarked":3},"submodules":[]},{"name":"EndList","counts":{"deprecated":0,"unstable":0,"stable":0,"unmarked":3},"submodules":[]},{"name":"EndQuery","counts":{"deprecated":0,"unstable":0,"stable":0,"unmarked":3},"submodules":[]},{"name":"EndTransformFeedback","counts":{"deprecated":0,"unstable":0,"stable":0,"unmarked":3},"submodules":[]},{"name":"EvalCoord1d","counts":{"deprecated":0,"unstable":0,"stable":0,"unmarked":3},"submodules":[]},{"name":"EvalCoord1dv","counts":{"deprecated":0,"unstable":0,"stable":0,"unmarked":3},"submodules":[]},{"name":"EvalCoord1f","counts":{"deprecated":0,"unstable":0,"stable":0,"unmarked":3},"submodules":[]},{"name":"EvalCoord1fv","counts":{"deprecated":0,"unstable":0,"stable":0,"unmarked":3},"submodules":[]},{"name":"EvalCoord2d","counts":{"deprecated":0,"unstable":0,"stable":0,"unmarked":3},"submodules":[]},{"name":"EvalCoord2dv","counts":{"deprecated":0,"unstable":0,"stable":0,"unmarked":3},"submodules":[]},{"name":"EvalCoord2f","counts":{"deprecated":0,"unstable":0,"stable":0,"unmarked":3},"submodules":[]},{"name":"EvalCoord2fv","counts":{"deprecated":0,"unstable":0,"stable":0,"unmarked":3},"submodules":[]},{"name":"EvalMesh1","counts":{"deprecated":0,"unstable":0,"stable":0,"unmarked":3},"submodules":[]},{"name":"EvalMesh2","counts":{"deprecated":0,"unstable":0,"stable":0,"unmarked":3},"submodules":[]},{"name":"EvalPoint1","counts":{"deprecated":0,"unstable":0,"stable":0,"unmarked":3},"submodules":[]},{"name":"EvalPoint2","counts":{"deprecated":0,"unstable":0,"stable":0,"unmarked":3},"submodules":[]},{"name":"FeedbackBuffer","counts":{"deprecated":0,"unstable":0,"stable":0,"unmarked":3},"submodules":[]},{"name":"Finish","counts":{"deprecated":0,"unstable":0,"stable":0,"unmarked":3},"submodules":[]},{"name":"Flush","counts":{"deprecated":0,"unstable":0,"stable":0,"unmarked":3},"submodules":[]},{"name":"FlushMappedBufferRange","counts":{"deprecated":0,"unstable":0,"stable":0,"unmarked":3},"submodules":[]},{"name":"FogCoordPointer","counts":{"deprecated":0,"unstable":0,"stable":0,"unmarked":3},"submodules":[]},{"name":"FogCoordd","counts":{"deprecated":0,"unstable":0,"stable":0,"unmarked":3},"submodules":[]},{"name":"FogCoorddv","counts":{"deprecated":0,"unstable":0,"stable":0,"unmarked":3},"submodules":[]},{"name":"FogCoordf","counts":{"deprecated":0,"unstable":0,"stable":0,"unmarked":3},"submodules":[]},{"name":"FogCoordfv","counts":{"deprecated":0,"unstable":0,"stable":0,"unmarked":3},"submodules":[]},{"name":"Fogf","counts":{"deprecated":0,"unstable":0,"stable":0,"unmarked":3},"submodules":[]},{"name":"Fogfv","counts":{"deprecated":0,"unstable":0,"stable":0,"unmarked":3},"submodules":[]},{"name":"Fogi","counts":{"deprecated":0,"unstable":0,"stable":0,"unmarked":3},"submodules":[]},{"name":"Fogiv","counts":{"deprecated":0,"unstable":0,"stable":0,"unmarked":3},"submodules":[]},{"name":"FramebufferRenderbuffer","counts":{"deprecated":0,"unstable":0,"stable":0,"unmarked":3},"submodules":[]},{"name":"FramebufferTexture1D","counts":{"deprecated":0,"unstable":0,"stable":0,"unmarked":3},"submodules":[]},{"name":"FramebufferTexture2D","counts":{"deprecated":0,"unstable":0,"stable":0,"unmarked":3},"submodules":[]},{"name":"FramebufferTexture3D","counts":{"deprecated":0,"unstable":0,"stable":0,"unmarked":3},"submodules":[]},{"name":"FramebufferTextureLayer","counts":{"deprecated":0,"unstable":0,"stable":0,"unmarked":3},"submodules":[]},{"name":"FrontFace","counts":{"deprecated":0,"unstable":0,"stable":0,"unmarked":3},"submodules":[]},{"name":"Frustum","counts":{"deprecated":0,"unstable":0,"stable":0,"unmarked":3},"submodules":[]},{"name":"GenBuffers","counts":{"deprecated":0,"unstable":0,"stable":0,"unmarked":3},"submodules":[]},{"name":"GenFramebuffers","counts":{"deprecated":0,"unstable":0,"stable":0,"unmarked":3},"submodules":[]},{"name":"GenLists","counts":{"deprecated":0,"unstable":0,"stable":0,"unmarked":3},"submodules":[]},{"name":"GenQueries","counts":{"deprecated":0,"unstable":0,"stable":0,"unmarked":3},"submodules":[]},{"name":"GenRenderbuffers","counts":{"deprecated":0,"unstable":0,"stable":0,"unmarked":3},"submodules":[]},{"name":"GenTextures","counts":{"deprecated":0,"unstable":0,"stable":0,"unmarked":3},"submodules":[]},{"name":"GenVertexArrays","counts":{"deprecated":0,"unstable":0,"stable":0,"unmarked":3},"submodules":[]},{"name":"GenerateMipmap","counts":{"deprecated":0,"unstable":0,"stable":0,"unmarked":3},"submodules":[]},{"name":"GetActiveAttrib","counts":{"deprecated":0,"unstable":0,"stable":0,"unmarked":3},"submodules":[]},{"name":"GetActiveUniform","counts":{"deprecated":0,"unstable":0,"stable":0,"unmarked":3},"submodules":[]},{"name":"GetAttachedShaders","counts":{"deprecated":0,"unstable":0,"stable":0,"unmarked":3},"submodules":[]},{"name":"GetAttribLocation","counts":{"deprecated":0,"unstable":0,"stable":0,"unmarked":3},"submodules":[]},{"name":"GetBooleani_v","counts":{"deprecated":0,"unstable":0,"stable":0,"unmarked":3},"submodules":[]},{"name":"GetBooleanv","counts":{"deprecated":0,"unstable":0,"stable":0,"unmarked":3},"submodules":[]},{"name":"GetBufferParameteriv","counts":{"deprecated":0,"unstable":0,"stable":0,"unmarked":3},"submodules":[]},{"name":"GetBufferPointerv","counts":{"deprecated":0,"unstable":0,"stable":0,"unmarked":3},"submodules":[]},{"name":"GetBufferSubData","counts":{"deprecated":0,"unstable":0,"stable":0,"unmarked":3},"submodules":[]},{"name":"GetClipPlane","counts":{"deprecated":0,"unstable":0,"stable":0,"unmarked":3},"submodules":[]},{"name":"GetCompressedTexImage","counts":{"deprecated":0,"unstable":0,"stable":0,"unmarked":3},"submodules":[]},{"name":"GetDoublev","counts":{"deprecated":0,"unstable":0,"stable":0,"unmarked":3},"submodules":[]},{"name":"GetError","counts":{"deprecated":0,"unstable":0,"stable":0,"unmarked":3},"submodules":[]},{"name":"GetFloatv","counts":{"deprecated":0,"unstable":0,"stable":0,"unmarked":3},"submodules":[]},{"name":"GetFragDataLocation","counts":{"deprecated":0,"unstable":0,"stable":0,"unmarked":3},"submodules":[]},{"name":"GetFramebufferAttachmentParameteriv","counts":{"deprecated":0,"unstable":0,"stable":0,"unmarked":3},"submodules":[]},{"name":"GetIntegeri_v","counts":{"deprecated":0,"unstable":0,"stable":0,"unmarked":3},"submodules":[]},{"name":"GetIntegerv","counts":{"deprecated":0,"unstable":0,"stable":0,"unmarked":3},"submodules":[]},{"name":"GetLightfv","counts":{"deprecated":0,"unstable":0,"stable":0,"unmarked":3},"submodules":[]},{"name":"GetLightiv","counts":{"deprecated":0,"unstable":0,"stable":0,"unmarked":3},"submodules":[]},{"name":"GetMapdv","counts":{"deprecated":0,"unstable":0,"stable":0,"unmarked":3},"submodules":[]},{"name":"GetMapfv","counts":{"deprecated":0,"unstable":0,"stable":0,"unmarked":3},"submodules":[]},{"name":"GetMapiv","counts":{"deprecated":0,"unstable":0,"stable":0,"unmarked":3},"submodules":[]},{"name":"GetMaterialfv","counts":{"deprecated":0,"unstable":0,"stable":0,"unmarked":3},"submodules":[]},{"name":"GetMaterialiv","counts":{"deprecated":0,"unstable":0,"stable":0,"unmarked":3},"submodules":[]},{"name":"GetPixelMapfv","counts":{"deprecated":0,"unstable":0,"stable":0,"unmarked":3},"submodules":[]},{"name":"GetPixelMapuiv","counts":{"deprecated":0,"unstable":0,"stable":0,"unmarked":3},"submodules":[]},{"name":"GetPixelMapusv","counts":{"deprecated":0,"unstable":0,"stable":0,"unmarked":3},"submodules":[]},{"name":"GetPointerv","counts":{"deprecated":0,"unstable":0,"stable":0,"unmarked":3},"submodules":[]},{"name":"GetPolygonStipple","counts":{"deprecated":0,"unstable":0,"stable":0,"unmarked":3},"submodules":[]},{"name":"GetProgramInfoLog","counts":{"deprecated":0,"unstable":0,"stable":0,"unmarked":3},"submodules":[]},{"name":"GetProgramiv","counts":{"deprecated":0,"unstable":0,"stable":0,"unmarked":3},"submodules":[]},{"name":"GetQueryObjectiv","counts":{"deprecated":0,"unstable":0,"stable":0,"unmarked":3},"submodules":[]},{"name":"GetQueryObjectuiv","counts":{"deprecated":0,"unstable":0,"stable":0,"unmarked":3},"submodules":[]},{"name":"GetQueryiv","counts":{"deprecated":0,"unstable":0,"stable":0,"unmarked":3},"submodules":[]},{"name":"GetRenderbufferParameteriv","counts":{"deprecated":0,"unstable":0,"stable":0,"unmarked":3},"submodules":[]},{"name":"GetShaderInfoLog","counts":{"deprecated":0,"unstable":0,"stable":0,"unmarked":3},"submodules":[]},{"name":"GetShaderSource","counts":{"deprecated":0,"unstable":0,"stable":0,"unmarked":3},"submodules":[]},{"name":"GetShaderiv","counts":{"deprecated":0,"unstable":0,"stable":0,"unmarked":3},"submodules":[]},{"name":"GetString","counts":{"deprecated":0,"unstable":0,"stable":0,"unmarked":3},"submodules":[]},{"name":"GetStringi","counts":{"deprecated":0,"unstable":0,"stable":0,"unmarked":3},"submodules":[]},{"name":"GetTexEnvfv","counts":{"deprecated":0,"unstable":0,"stable":0,"unmarked":3},"submodules":[]},{"name":"GetTexEnviv","counts":{"deprecated":0,"unstable":0,"stable":0,"unmarked":3},"submodules":[]},{"name":"GetTexGendv","counts":{"deprecated":0,"unstable":0,"stable":0,"unmarked":3},"submodules":[]},{"name":"GetTexGenfv","counts":{"deprecated":0,"unstable":0,"stable":0,"unmarked":3},"submodules":[]},{"name":"GetTexGeniv","counts":{"deprecated":0,"unstable":0,"stable":0,"unmarked":3},"submodules":[]},{"name":"GetTexImage","counts":{"deprecated":0,"unstable":0,"stable":0,"unmarked":3},"submodules":[]},{"name":"GetTexLevelParameterfv","counts":{"deprecated":0,"unstable":0,"stable":0,"unmarked":3},"submodules":[]},{"name":"GetTexLevelParameteriv","counts":{"deprecated":0,"unstable":0,"stable":0,"unmarked":3},"submodules":[]},{"name":"GetTexParameterIiv","counts":{"deprecated":0,"unstable":0,"stable":0,"unmarked":3},"submodules":[]},{"name":"GetTexParameterIuiv","counts":{"deprecated":0,"unstable":0,"stable":0,"unmarked":3},"submodules":[]},{"name":"GetTexParameterfv","counts":{"deprecated":0,"unstable":0,"stable":0,"unmarked":3},"submodules":[]},{"name":"GetTexParameteriv","counts":{"deprecated":0,"unstable":0,"stable":0,"unmarked":3},"submodules":[]},{"name":"GetTransformFeedbackVarying","counts":{"deprecated":0,"unstable":0,"stable":0,"unmarked":3},"submodules":[]},{"name":"GetUniformLocation","counts":{"deprecated":0,"unstable":0,"stable":0,"unmarked":3},"submodules":[]},{"name":"GetUniformfv","counts":{"deprecated":0,"unstable":0,"stable":0,"unmarked":3},"submodules":[]},{"name":"GetUniformiv","counts":{"deprecated":0,"unstable":0,"stable":0,"unmarked":3},"submodules":[]},{"name":"GetUniformuiv","counts":{"deprecated":0,"unstable":0,"stable":0,"unmarked":3},"submodules":[]},{"name":"GetVertexAttribIiv","counts":{"deprecated":0,"unstable":0,"stable":0,"unmarked":3},"submodules":[]},{"name":"GetVertexAttribIuiv","counts":{"deprecated":0,"unstable":0,"stable":0,"unmarked":3},"submodules":[]},{"name":"GetVertexAttribPointerv","counts":{"deprecated":0,"unstable":0,"stable":0,"unmarked":3},"submodules":[]},{"name":"GetVertexAttribdv","counts":{"deprecated":0,"unstable":0,"stable":0,"unmarked":3},"submodules":[]},{"name":"GetVertexAttribfv","counts":{"deprecated":0,"unstable":0,"stable":0,"unmarked":3},"submodules":[]},{"name":"GetVertexAttribiv","counts":{"deprecated":0,"unstable":0,"stable":0,"unmarked":3},"submodules":[]},{"name":"Hint","counts":{"deprecated":0,"unstable":0,"stable":0,"unmarked":3},"submodules":[]},{"name":"IndexMask","counts":{"deprecated":0,"unstable":0,"stable":0,"unmarked":3},"submodules":[]},{"name":"IndexPointer","counts":{"deprecated":0,"unstable":0,"stable":0,"unmarked":3},"submodules":[]},{"name":"Indexd","counts":{"deprecated":0,"unstable":0,"stable":0,"unmarked":3},"submodules":[]},{"name":"Indexdv","counts":{"deprecated":0,"unstable":0,"stable":0,"unmarked":3},"submodules":[]},{"name":"Indexf","counts":{"deprecated":0,"unstable":0,"stable":0,"unmarked":3},"submodules":[]},{"name":"Indexfv","counts":{"deprecated":0,"unstable":0,"stable":0,"unmarked":3},"submodules":[]},{"name":"Indexi","counts":{"deprecated":0,"unstable":0,"stable":0,"unmarked":3},"submodules":[]},{"name":"Indexiv","counts":{"deprecated":0,"unstable":0,"stable":0,"unmarked":3},"submodules":[]},{"name":"Indexs","counts":{"deprecated":0,"unstable":0,"stable":0,"unmarked":3},"submodules":[]},{"name":"Indexsv","counts":{"deprecated":0,"unstable":0,"stable":0,"unmarked":3},"submodules":[]},{"name":"Indexub","counts":{"deprecated":0,"unstable":0,"stable":0,"unmarked":3},"submodules":[]},{"name":"Indexubv","counts":{"deprecated":0,"unstable":0,"stable":0,"unmarked":3},"submodules":[]},{"name":"InitNames","counts":{"deprecated":0,"unstable":0,"stable":0,"unmarked":3},"submodules":[]},{"name":"InterleavedArrays","counts":{"deprecated":0,"unstable":0,"stable":0,"unmarked":3},"submodules":[]},{"name":"IsBuffer","counts":{"deprecated":0,"unstable":0,"stable":0,"unmarked":3},"submodules":[]},{"name":"IsEnabled","counts":{"deprecated":0,"unstable":0,"stable":0,"unmarked":3},"submodules":[]},{"name":"IsEnabledi","counts":{"deprecated":0,"unstable":0,"stable":0,"unmarked":3},"submodules":[]},{"name":"IsFramebuffer","counts":{"deprecated":0,"unstable":0,"stable":0,"unmarked":3},"submodules":[]},{"name":"IsList","counts":{"deprecated":0,"unstable":0,"stable":0,"unmarked":3},"submodules":[]},{"name":"IsProgram","counts":{"deprecated":0,"unstable":0,"stable":0,"unmarked":3},"submodules":[]},{"name":"IsQuery","counts":{"deprecated":0,"unstable":0,"stable":0,"unmarked":3},"submodules":[]},{"name":"IsRenderbuffer","counts":{"deprecated":0,"unstable":0,"stable":0,"unmarked":3},"submodules":[]},{"name":"IsShader","counts":{"deprecated":0,"unstable":0,"stable":0,"unmarked":3},"submodules":[]},{"name":"IsTexture","counts":{"deprecated":0,"unstable":0,"stable":0,"unmarked":3},"submodules":[]},{"name":"IsVertexArray","counts":{"deprecated":0,"unstable":0,"stable":0,"unmarked":3},"submodules":[]},{"name":"LightModelf","counts":{"deprecated":0,"unstable":0,"stable":0,"unmarked":3},"submodules":[]},{"name":"LightModelfv","counts":{"deprecated":0,"unstable":0,"stable":0,"unmarked":3},"submodules":[]},{"name":"LightModeli","counts":{"deprecated":0,"unstable":0,"stable":0,"unmarked":3},"submodules":[]},{"name":"LightModeliv","counts":{"deprecated":0,"unstable":0,"stable":0,"unmarked":3},"submodules":[]},{"name":"Lightf","counts":{"deprecated":0,"unstable":0,"stable":0,"unmarked":3},"submodules":[]},{"name":"Lightfv","counts":{"deprecated":0,"unstable":0,"stable":0,"unmarked":3},"submodules":[]},{"name":"Lighti","counts":{"deprecated":0,"unstable":0,"stable":0,"unmarked":3},"submodules":[]},{"name":"Lightiv","counts":{"deprecated":0,"unstable":0,"stable":0,"unmarked":3},"submodules":[]},{"name":"LineStipple","counts":{"deprecated":0,"unstable":0,"stable":0,"unmarked":3},"submodules":[]},{"name":"LineWidth","counts":{"deprecated":0,"unstable":0,"stable":0,"unmarked":3},"submodules":[]},{"name":"LinkProgram","counts":{"deprecated":0,"unstable":0,"stable":0,"unmarked":3},"submodules":[]},{"name":"ListBase","counts":{"deprecated":0,"unstable":0,"stable":0,"unmarked":3},"submodules":[]},{"name":"LoadIdentity","counts":{"deprecated":0,"unstable":0,"stable":0,"unmarked":3},"submodules":[]},{"name":"LoadMatrixd","counts":{"deprecated":0,"unstable":0,"stable":0,"unmarked":3},"submodules":[]},{"name":"LoadMatrixf","counts":{"deprecated":0,"unstable":0,"stable":0,"unmarked":3},"submodules":[]},{"name":"LoadName","counts":{"deprecated":0,"unstable":0,"stable":0,"unmarked":3},"submodules":[]},{"name":"LoadTransposeMatrixd","counts":{"deprecated":0,"unstable":0,"stable":0,"unmarked":3},"submodules":[]},{"name":"LoadTransposeMatrixf","counts":{"deprecated":0,"unstable":0,"stable":0,"unmarked":3},"submodules":[]},{"name":"LogicOp","counts":{"deprecated":0,"unstable":0,"stable":0,"unmarked":3},"submodules":[]},{"name":"Map1d","counts":{"deprecated":0,"unstable":0,"stable":0,"unmarked":3},"submodules":[]},{"name":"Map1f","counts":{"deprecated":0,"unstable":0,"stable":0,"unmarked":3},"submodules":[]},{"name":"Map2d","counts":{"deprecated":0,"unstable":0,"stable":0,"unmarked":3},"submodules":[]},{"name":"Map2f","counts":{"deprecated":0,"unstable":0,"stable":0,"unmarked":3},"submodules":[]},{"name":"MapBuffer","counts":{"deprecated":0,"unstable":0,"stable":0,"unmarked":3},"submodules":[]},{"name":"MapBufferRange","counts":{"deprecated":0,"unstable":0,"stable":0,"unmarked":3},"submodules":[]},{"name":"MapGrid1d","counts":{"deprecated":0,"unstable":0,"stable":0,"unmarked":3},"submodules":[]},{"name":"MapGrid1f","counts":{"deprecated":0,"unstable":0,"stable":0,"unmarked":3},"submodules":[]},{"name":"MapGrid2d","counts":{"deprecated":0,"unstable":0,"stable":0,"unmarked":3},"submodules":[]},{"name":"MapGrid2f","counts":{"deprecated":0,"unstable":0,"stable":0,"unmarked":3},"submodules":[]},{"name":"Materialf","counts":{"deprecated":0,"unstable":0,"stable":0,"unmarked":3},"submodules":[]},{"name":"Materialfv","counts":{"deprecated":0,"unstable":0,"stable":0,"unmarked":3},"submodules":[]},{"name":"Materiali","counts":{"deprecated":0,"unstable":0,"stable":0,"unmarked":3},"submodules":[]},{"name":"Materialiv","counts":{"deprecated":0,"unstable":0,"stable":0,"unmarked":3},"submodules":[]},{"name":"MatrixMode","counts":{"deprecated":0,"unstable":0,"stable":0,"unmarked":3},"submodules":[]},{"name":"MultMatrixd","counts":{"deprecated":0,"unstable":0,"stable":0,"unmarked":3},"submodules":[]},{"name":"MultMatrixf","counts":{"deprecated":0,"unstable":0,"stable":0,"unmarked":3},"submodules":[]},{"name":"MultTransposeMatrixd","counts":{"deprecated":0,"unstable":0,"stable":0,"unmarked":3},"submodules":[]},{"name":"MultTransposeMatrixf","counts":{"deprecated":0,"unstable":0,"stable":0,"unmarked":3},"submodules":[]},{"name":"MultiDrawArrays","counts":{"deprecated":0,"unstable":0,"stable":0,"unmarked":3},"submodules":[]},{"name":"MultiDrawElements","counts":{"deprecated":0,"unstable":0,"stable":0,"unmarked":3},"submodules":[]},{"name":"MultiTexCoord1d","counts":{"deprecated":0,"unstable":0,"stable":0,"unmarked":3},"submodules":[]},{"name":"MultiTexCoord1dv","counts":{"deprecated":0,"unstable":0,"stable":0,"unmarked":3},"submodules":[]},{"name":"MultiTexCoord1f","counts":{"deprecated":0,"unstable":0,"stable":0,"unmarked":3},"submodules":[]},{"name":"MultiTexCoord1fv","counts":{"deprecated":0,"unstable":0,"stable":0,"unmarked":3},"submodules":[]},{"name":"MultiTexCoord1i","counts":{"deprecated":0,"unstable":0,"stable":0,"unmarked":3},"submodules":[]},{"name":"MultiTexCoord1iv","counts":{"deprecated":0,"unstable":0,"stable":0,"unmarked":3},"submodules":[]},{"name":"MultiTexCoord1s","counts":{"deprecated":0,"unstable":0,"stable":0,"unmarked":3},"submodules":[]},{"name":"MultiTexCoord1sv","counts":{"deprecated":0,"unstable":0,"stable":0,"unmarked":3},"submodules":[]},{"name":"MultiTexCoord2d","counts":{"deprecated":0,"unstable":0,"stable":0,"unmarked":3},"submodules":[]},{"name":"MultiTexCoord2dv","counts":{"deprecated":0,"unstable":0,"stable":0,"unmarked":3},"submodules":[]},{"name":"MultiTexCoord2f","counts":{"deprecated":0,"unstable":0,"stable":0,"unmarked":3},"submodules":[]},{"name":"MultiTexCoord2fv","counts":{"deprecated":0,"unstable":0,"stable":0,"unmarked":3},"submodules":[]},{"name":"MultiTexCoord2i","counts":{"deprecated":0,"unstable":0,"stable":0,"unmarked":3},"submodules":[]},{"name":"MultiTexCoord2iv","counts":{"deprecated":0,"unstable":0,"stable":0,"unmarked":3},"submodules":[]},{"name":"MultiTexCoord2s","counts":{"deprecated":0,"unstable":0,"stable":0,"unmarked":3},"submodules":[]},{"name":"MultiTexCoord2sv","counts":{"deprecated":0,"unstable":0,"stable":0,"unmarked":3},"submodules":[]},{"name":"MultiTexCoord3d","counts":{"deprecated":0,"unstable":0,"stable":0,"unmarked":3},"submodules":[]},{"name":"MultiTexCoord3dv","counts":{"deprecated":0,"unstable":0,"stable":0,"unmarked":3},"submodules":[]},{"name":"MultiTexCoord3f","counts":{"deprecated":0,"unstable":0,"stable":0,"unmarked":3},"submodules":[]},{"name":"MultiTexCoord3fv","counts":{"deprecated":0,"unstable":0,"stable":0,"unmarked":3},"submodules":[]},{"name":"MultiTexCoord3i","counts":{"deprecated":0,"unstable":0,"stable":0,"unmarked":3},"submodules":[]},{"name":"MultiTexCoord3iv","counts":{"deprecated":0,"unstable":0,"stable":0,"unmarked":3},"submodules":[]},{"name":"MultiTexCoord3s","counts":{"deprecated":0,"unstable":0,"stable":0,"unmarked":3},"submodules":[]},{"name":"MultiTexCoord3sv","counts":{"deprecated":0,"unstable":0,"stable":0,"unmarked":3},"submodules":[]},{"name":"MultiTexCoord4d","counts":{"deprecated":0,"unstable":0,"stable":0,"unmarked":3},"submodules":[]},{"name":"MultiTexCoord4dv","counts":{"deprecated":0,"unstable":0,"stable":0,"unmarked":3},"submodules":[]},{"name":"MultiTexCoord4f","counts":{"deprecated":0,"unstable":0,"stable":0,"unmarked":3},"submodules":[]},{"name":"MultiTexCoord4fv","counts":{"deprecated":0,"unstable":0,"stable":0,"unmarked":3},"submodules":[]},{"name":"MultiTexCoord4i","counts":{"deprecated":0,"unstable":0,"stable":0,"unmarked":3},"submodules":[]},{"name":"MultiTexCoord4iv","counts":{"deprecated":0,"unstable":0,"stable":0,"unmarked":3},"submodules":[]},{"name":"MultiTexCoord4s","counts":{"deprecated":0,"unstable":0,"stable":0,"unmarked":3},"submodules":[]},{"name":"MultiTexCoord4sv","counts":{"deprecated":0,"unstable":0,"stable":0,"unmarked":3},"submodules":[]},{"name":"NewList","counts":{"deprecated":0,"unstable":0,"stable":0,"unmarked":3},"submodules":[]},{"name":"Normal3b","counts":{"deprecated":0,"unstable":0,"stable":0,"unmarked":3},"submodules":[]},{"name":"Normal3bv","counts":{"deprecated":0,"unstable":0,"stable":0,"unmarked":3},"submodules":[]},{"name":"Normal3d","counts":{"deprecated":0,"unstable":0,"stable":0,"unmarked":3},"submodules":[]},{"name":"Normal3dv","counts":{"deprecated":0,"unstable":0,"stable":0,"unmarked":3},"submodules":[]},{"name":"Normal3f","counts":{"deprecated":0,"unstable":0,"stable":0,"unmarked":3},"submodules":[]},{"name":"Normal3fv","counts":{"deprecated":0,"unstable":0,"stable":0,"unmarked":3},"submodules":[]},{"name":"Normal3i","counts":{"deprecated":0,"unstable":0,"stable":0,"unmarked":3},"submodules":[]},{"name":"Normal3iv","counts":{"deprecated":0,"unstable":0,"stable":0,"unmarked":3},"submodules":[]},{"name":"Normal3s","counts":{"deprecated":0,"unstable":0,"stable":0,"unmarked":3},"submodules":[]},{"name":"Normal3sv","counts":{"deprecated":0,"unstable":0,"stable":0,"unmarked":3},"submodules":[]},{"name":"NormalPointer","counts":{"deprecated":0,"unstable":0,"stable":0,"unmarked":3},"submodules":[]},{"name":"Ortho","counts":{"deprecated":0,"unstable":0,"stable":0,"unmarked":3},"submodules":[]},{"name":"PassThrough","counts":{"deprecated":0,"unstable":0,"stable":0,"unmarked":3},"submodules":[]},{"name":"PixelMapfv","counts":{"deprecated":0,"unstable":0,"stable":0,"unmarked":3},"submodules":[]},{"name":"PixelMapuiv","counts":{"deprecated":0,"unstable":0,"stable":0,"unmarked":3},"submodules":[]},{"name":"PixelMapusv","counts":{"deprecated":0,"unstable":0,"stable":0,"unmarked":3},"submodules":[]},{"name":"PixelStoref","counts":{"deprecated":0,"unstable":0,"stable":0,"unmarked":3},"submodules":[]},{"name":"PixelStorei","counts":{"deprecated":0,"unstable":0,"stable":0,"unmarked":3},"submodules":[]},{"name":"PixelTransferf","counts":{"deprecated":0,"unstable":0,"stable":0,"unmarked":3},"submodules":[]},{"name":"PixelTransferi","counts":{"deprecated":0,"unstable":0,"stable":0,"unmarked":3},"submodules":[]},{"name":"PixelZoom","counts":{"deprecated":0,"unstable":0,"stable":0,"unmarked":3},"submodules":[]},{"name":"PointParameterf","counts":{"deprecated":0,"unstable":0,"stable":0,"unmarked":3},"submodules":[]},{"name":"PointParameterfv","counts":{"deprecated":0,"unstable":0,"stable":0,"unmarked":3},"submodules":[]},{"name":"PointParameteri","counts":{"deprecated":0,"unstable":0,"stable":0,"unmarked":3},"submodules":[]},{"name":"PointParameteriv","counts":{"deprecated":0,"unstable":0,"stable":0,"unmarked":3},"submodules":[]},{"name":"PointSize","counts":{"deprecated":0,"unstable":0,"stable":0,"unmarked":3},"submodules":[]},{"name":"PolygonMode","counts":{"deprecated":0,"unstable":0,"stable":0,"unmarked":3},"submodules":[]},{"name":"PolygonOffset","counts":{"deprecated":0,"unstable":0,"stable":0,"unmarked":3},"submodules":[]},{"name":"PolygonStipple","counts":{"deprecated":0,"unstable":0,"stable":0,"unmarked":3},"submodules":[]},{"name":"PopAttrib","counts":{"deprecated":0,"unstable":0,"stable":0,"unmarked":3},"submodules":[]},{"name":"PopClientAttrib","counts":{"deprecated":0,"unstable":0,"stable":0,"unmarked":3},"submodules":[]},{"name":"PopMatrix","counts":{"deprecated":0,"unstable":0,"stable":0,"unmarked":3},"submodules":[]},{"name":"PopName","counts":{"deprecated":0,"unstable":0,"stable":0,"unmarked":3},"submodules":[]},{"name":"PrioritizeTextures","counts":{"deprecated":0,"unstable":0,"stable":0,"unmarked":3},"submodules":[]},{"name":"PushAttrib","counts":{"deprecated":0,"unstable":0,"stable":0,"unmarked":3},"submodules":[]},{"name":"PushClientAttrib","counts":{"deprecated":0,"unstable":0,"stable":0,"unmarked":3},"submodules":[]},{"name":"PushMatrix","counts":{"deprecated":0,"unstable":0,"stable":0,"unmarked":3},"submodules":[]},{"name":"PushName","counts":{"deprecated":0,"unstable":0,"stable":0,"unmarked":3},"submodules":[]},{"name":"RasterPos2d","counts":{"deprecated":0,"unstable":0,"stable":0,"unmarked":3},"submodules":[]},{"name":"RasterPos2dv","counts":{"deprecated":0,"unstable":0,"stable":0,"unmarked":3},"submodules":[]},{"name":"RasterPos2f","counts":{"deprecated":0,"unstable":0,"stable":0,"unmarked":3},"submodules":[]},{"name":"RasterPos2fv","counts":{"deprecated":0,"unstable":0,"stable":0,"unmarked":3},"submodules":[]},{"name":"RasterPos2i","counts":{"deprecated":0,"unstable":0,"stable":0,"unmarked":3},"submodules":[]},{"name":"RasterPos2iv","counts":{"deprecated":0,"unstable":0,"stable":0,"unmarked":3},"submodules":[]},{"name":"RasterPos2s","counts":{"deprecated":0,"unstable":0,"stable":0,"unmarked":3},"submodules":[]},{"name":"RasterPos2sv","counts":{"deprecated":0,"unstable":0,"stable":0,"unmarked":3},"submodules":[]},{"name":"RasterPos3d","counts":{"deprecated":0,"unstable":0,"stable":0,"unmarked":3},"submodules":[]},{"name":"RasterPos3dv","counts":{"deprecated":0,"unstable":0,"stable":0,"unmarked":3},"submodules":[]},{"name":"RasterPos3f","counts":{"deprecated":0,"unstable":0,"stable":0,"unmarked":3},"submodules":[]},{"name":"RasterPos3fv","counts":{"deprecated":0,"unstable":0,"stable":0,"unmarked":3},"submodules":[]},{"name":"RasterPos3i","counts":{"deprecated":0,"unstable":0,"stable":0,"unmarked":3},"submodules":[]},{"name":"RasterPos3iv","counts":{"deprecated":0,"unstable":0,"stable":0,"unmarked":3},"submodules":[]},{"name":"RasterPos3s","counts":{"deprecated":0,"unstable":0,"stable":0,"unmarked":3},"submodules":[]},{"name":"RasterPos3sv","counts":{"deprecated":0,"unstable":0,"stable":0,"unmarked":3},"submodules":[]},{"name":"RasterPos4d","counts":{"deprecated":0,"unstable":0,"stable":0,"unmarked":3},"submodules":[]},{"name":"RasterPos4dv","counts":{"deprecated":0,"unstable":0,"stable":0,"unmarked":3},"submodules":[]},{"name":"RasterPos4f","counts":{"deprecated":0,"unstable":0,"stable":0,"unmarked":3},"submodules":[]},{"name":"RasterPos4fv","counts":{"deprecated":0,"unstable":0,"stable":0,"unmarked":3},"submodules":[]},{"name":"RasterPos4i","counts":{"deprecated":0,"unstable":0,"stable":0,"unmarked":3},"submodules":[]},{"name":"RasterPos4iv","counts":{"deprecated":0,"unstable":0,"stable":0,"unmarked":3},"submodules":[]},{"name":"RasterPos4s","counts":{"deprecated":0,"unstable":0,"stable":0,"unmarked":3},"submodules":[]},{"name":"RasterPos4sv","counts":{"deprecated":0,"unstable":0,"stable":0,"unmarked":3},"submodules":[]},{"name":"ReadBuffer","counts":{"deprecated":0,"unstable":0,"stable":0,"unmarked":3},"submodules":[]},{"name":"ReadPixels","counts":{"deprecated":0,"unstable":0,"stable":0,"unmarked":3},"submodules":[]},{"name":"Rectd","counts":{"deprecated":0,"unstable":0,"stable":0,"unmarked":3},"submodules":[]},{"name":"Rectdv","counts":{"deprecated":0,"unstable":0,"stable":0,"unmarked":3},"submodules":[]},{"name":"Rectf","counts":{"deprecated":0,"unstable":0,"stable":0,"unmarked":3},"submodules":[]},{"name":"Rectfv","counts":{"deprecated":0,"unstable":0,"stable":0,"unmarked":3},"submodules":[]},{"name":"Recti","counts":{"deprecated":0,"unstable":0,"stable":0,"unmarked":3},"submodules":[]},{"name":"Rectiv","counts":{"deprecated":0,"unstable":0,"stable":0,"unmarked":3},"submodules":[]},{"name":"Rects","counts":{"deprecated":0,"unstable":0,"stable":0,"unmarked":3},"submodules":[]},{"name":"Rectsv","counts":{"deprecated":0,"unstable":0,"stable":0,"unmarked":3},"submodules":[]},{"name":"RenderMode","counts":{"deprecated":0,"unstable":0,"stable":0,"unmarked":3},"submodules":[]},{"name":"RenderbufferStorage","counts":{"deprecated":0,"unstable":0,"stable":0,"unmarked":3},"submodules":[]},{"name":"RenderbufferStorageMultisample","counts":{"deprecated":0,"unstable":0,"stable":0,"unmarked":3},"submodules":[]},{"name":"Rotated","counts":{"deprecated":0,"unstable":0,"stable":0,"unmarked":3},"submodules":[]},{"name":"Rotatef","counts":{"deprecated":0,"unstable":0,"stable":0,"unmarked":3},"submodules":[]},{"name":"SampleCoverage","counts":{"deprecated":0,"unstable":0,"stable":0,"unmarked":3},"submodules":[]},{"name":"Scaled","counts":{"deprecated":0,"unstable":0,"stable":0,"unmarked":3},"submodules":[]},{"name":"Scalef","counts":{"deprecated":0,"unstable":0,"stable":0,"unmarked":3},"submodules":[]},{"name":"Scissor","counts":{"deprecated":0,"unstable":0,"stable":0,"unmarked":3},"submodules":[]},{"name":"SecondaryColor3b","counts":{"deprecated":0,"unstable":0,"stable":0,"unmarked":3},"submodules":[]},{"name":"SecondaryColor3bv","counts":{"deprecated":0,"unstable":0,"stable":0,"unmarked":3},"submodules":[]},{"name":"SecondaryColor3d","counts":{"deprecated":0,"unstable":0,"stable":0,"unmarked":3},"submodules":[]},{"name":"SecondaryColor3dv","counts":{"deprecated":0,"unstable":0,"stable":0,"unmarked":3},"submodules":[]},{"name":"SecondaryColor3f","counts":{"deprecated":0,"unstable":0,"stable":0,"unmarked":3},"submodules":[]},{"name":"SecondaryColor3fv","counts":{"deprecated":0,"unstable":0,"stable":0,"unmarked":3},"submodules":[]},{"name":"SecondaryColor3i","counts":{"deprecated":0,"unstable":0,"stable":0,"unmarked":3},"submodules":[]},{"name":"SecondaryColor3iv","counts":{"deprecated":0,"unstable":0,"stable":0,"unmarked":3},"submodules":[]},{"name":"SecondaryColor3s","counts":{"deprecated":0,"unstable":0,"stable":0,"unmarked":3},"submodules":[]},{"name":"SecondaryColor3sv","counts":{"deprecated":0,"unstable":0,"stable":0,"unmarked":3},"submodules":[]},{"name":"SecondaryColor3ub","counts":{"deprecated":0,"unstable":0,"stable":0,"unmarked":3},"submodules":[]},{"name":"SecondaryColor3ubv","counts":{"deprecated":0,"unstable":0,"stable":0,"unmarked":3},"submodules":[]},{"name":"SecondaryColor3ui","counts":{"deprecated":0,"unstable":0,"stable":0,"unmarked":3},"submodules":[]},{"name":"SecondaryColor3uiv","counts":{"deprecated":0,"unstable":0,"stable":0,"unmarked":3},"submodules":[]},{"name":"SecondaryColor3us","counts":{"deprecated":0,"unstable":0,"stable":0,"unmarked":3},"submodules":[]},{"name":"SecondaryColor3usv","counts":{"deprecated":0,"unstable":0,"stable":0,"unmarked":3},"submodules":[]},{"name":"SecondaryColorPointer","counts":{"deprecated":0,"unstable":0,"stable":0,"unmarked":3},"submodules":[]},{"name":"SelectBuffer","counts":{"deprecated":0,"unstable":0,"stable":0,"unmarked":3},"submodules":[]},{"name":"ShadeModel","counts":{"deprecated":0,"unstable":0,"stable":0,"unmarked":3},"submodules":[]},{"name":"ShaderSource","counts":{"deprecated":0,"unstable":0,"stable":0,"unmarked":3},"submodules":[]},{"name":"StencilFunc","counts":{"deprecated":0,"unstable":0,"stable":0,"unmarked":3},"submodules":[]},{"name":"StencilFuncSeparate","counts":{"deprecated":0,"unstable":0,"stable":0,"unmarked":3},"submodules":[]},{"name":"StencilMask","counts":{"deprecated":0,"unstable":0,"stable":0,"unmarked":3},"submodules":[]},{"name":"StencilMaskSeparate","counts":{"deprecated":0,"unstable":0,"stable":0,"unmarked":3},"submodules":[]},{"name":"StencilOp","counts":{"deprecated":0,"unstable":0,"stable":0,"unmarked":3},"submodules":[]},{"name":"StencilOpSeparate","counts":{"deprecated":0,"unstable":0,"stable":0,"unmarked":3},"submodules":[]},{"name":"TexCoord1d","counts":{"deprecated":0,"unstable":0,"stable":0,"unmarked":3},"submodules":[]},{"name":"TexCoord1dv","counts":{"deprecated":0,"unstable":0,"stable":0,"unmarked":3},"submodules":[]},{"name":"TexCoord1f","counts":{"deprecated":0,"unstable":0,"stable":0,"unmarked":3},"submodules":[]},{"name":"TexCoord1fv","counts":{"deprecated":0,"unstable":0,"stable":0,"unmarked":3},"submodules":[]},{"name":"TexCoord1i","counts":{"deprecated":0,"unstable":0,"stable":0,"unmarked":3},"submodules":[]},{"name":"TexCoord1iv","counts":{"deprecated":0,"unstable":0,"stable":0,"unmarked":3},"submodules":[]},{"name":"TexCoord1s","counts":{"deprecated":0,"unstable":0,"stable":0,"unmarked":3},"submodules":[]},{"name":"TexCoord1sv","counts":{"deprecated":0,"unstable":0,"stable":0,"unmarked":3},"submodules":[]},{"name":"TexCoord2d","counts":{"deprecated":0,"unstable":0,"stable":0,"unmarked":3},"submodules":[]},{"name":"TexCoord2dv","counts":{"deprecated":0,"unstable":0,"stable":0,"unmarked":3},"submodules":[]},{"name":"TexCoord2f","counts":{"deprecated":0,"unstable":0,"stable":0,"unmarked":3},"submodules":[]},{"name":"TexCoord2fv","counts":{"deprecated":0,"unstable":0,"stable":0,"unmarked":3},"submodules":[]},{"name":"TexCoord2i","counts":{"deprecated":0,"unstable":0,"stable":0,"unmarked":3},"submodules":[]},{"name":"TexCoord2iv","counts":{"deprecated":0,"unstable":0,"stable":0,"unmarked":3},"submodules":[]},{"name":"TexCoord2s","counts":{"deprecated":0,"unstable":0,"stable":0,"unmarked":3},"submodules":[]},{"name":"TexCoord2sv","counts":{"deprecated":0,"unstable":0,"stable":0,"unmarked":3},"submodules":[]},{"name":"TexCoord3d","counts":{"deprecated":0,"unstable":0,"stable":0,"unmarked":3},"submodules":[]},{"name":"TexCoord3dv","counts":{"deprecated":0,"unstable":0,"stable":0,"unmarked":3},"submodules":[]},{"name":"TexCoord3f","counts":{"deprecated":0,"unstable":0,"stable":0,"unmarked":3},"submodules":[]},{"name":"TexCoord3fv","counts":{"deprecated":0,"unstable":0,"stable":0,"unmarked":3},"submodules":[]},{"name":"TexCoord3i","counts":{"deprecated":0,"unstable":0,"stable":0,"unmarked":3},"submodules":[]},{"name":"TexCoord3iv","counts":{"deprecated":0,"unstable":0,"stable":0,"unmarked":3},"submodules":[]},{"name":"TexCoord3s","counts":{"deprecated":0,"unstable":0,"stable":0,"unmarked":3},"submodules":[]},{"name":"TexCoord3sv","counts":{"deprecated":0,"unstable":0,"stable":0,"unmarked":3},"submodules":[]},{"name":"TexCoord4d","counts":{"deprecated":0,"unstable":0,"stable":0,"unmarked":3},"submodules":[]},{"name":"TexCoord4dv","counts":{"deprecated":0,"unstable":0,"stable":0,"unmarked":3},"submodules":[]},{"name":"TexCoord4f","counts":{"deprecated":0,"unstable":0,"stable":0,"unmarked":3},"submodules":[]},{"name":"TexCoord4fv","counts":{"deprecated":0,"unstable":0,"stable":0,"unmarked":3},"submodules":[]},{"name":"TexCoord4i","counts":{"deprecated":0,"unstable":0,"stable":0,"unmarked":3},"submodules":[]},{"name":"TexCoord4iv","counts":{"deprecated":0,"unstable":0,"stable":0,"unmarked":3},"submodules":[]},{"name":"TexCoord4s","counts":{"deprecated":0,"unstable":0,"stable":0,"unmarked":3},"submodules":[]},{"name":"TexCoord4sv","counts":{"deprecated":0,"unstable":0,"stable":0,"unmarked":3},"submodules":[]},{"name":"TexCoordPointer","counts":{"deprecated":0,"unstable":0,"stable":0,"unmarked":3},"submodules":[]},{"name":"TexEnvf","counts":{"deprecated":0,"unstable":0,"stable":0,"unmarked":3},"submodules":[]},{"name":"TexEnvfv","counts":{"deprecated":0,"unstable":0,"stable":0,"unmarked":3},"submodules":[]},{"name":"TexEnvi","counts":{"deprecated":0,"unstable":0,"stable":0,"unmarked":3},"submodules":[]},{"name":"TexEnviv","counts":{"deprecated":0,"unstable":0,"stable":0,"unmarked":3},"submodules":[]},{"name":"TexGend","counts":{"deprecated":0,"unstable":0,"stable":0,"unmarked":3},"submodules":[]},{"name":"TexGendv","counts":{"deprecated":0,"unstable":0,"stable":0,"unmarked":3},"submodules":[]},{"name":"TexGenf","counts":{"deprecated":0,"unstable":0,"stable":0,"unmarked":3},"submodules":[]},{"name":"TexGenfv","counts":{"deprecated":0,"unstable":0,"stable":0,"unmarked":3},"submodules":[]},{"name":"TexGeni","counts":{"deprecated":0,"unstable":0,"stable":0,"unmarked":3},"submodules":[]},{"name":"TexGeniv","counts":{"deprecated":0,"unstable":0,"stable":0,"unmarked":3},"submodules":[]},{"name":"TexImage1D","counts":{"deprecated":0,"unstable":0,"stable":0,"unmarked":3},"submodules":[]},{"name":"TexImage2D","counts":{"deprecated":0,"unstable":0,"stable":0,"unmarked":3},"submodules":[]},{"name":"TexImage3D","counts":{"deprecated":0,"unstable":0,"stable":0,"unmarked":3},"submodules":[]},{"name":"TexParameterIiv","counts":{"deprecated":0,"unstable":0,"stable":0,"unmarked":3},"submodules":[]},{"name":"TexParameterIuiv","counts":{"deprecated":0,"unstable":0,"stable":0,"unmarked":3},"submodules":[]},{"name":"TexParameterf","counts":{"deprecated":0,"unstable":0,"stable":0,"unmarked":3},"submodules":[]},{"name":"TexParameterfv","counts":{"deprecated":0,"unstable":0,"stable":0,"unmarked":3},"submodules":[]},{"name":"TexParameteri","counts":{"deprecated":0,"unstable":0,"stable":0,"unmarked":3},"submodules":[]},{"name":"TexParameteriv","counts":{"deprecated":0,"unstable":0,"stable":0,"unmarked":3},"submodules":[]},{"name":"TexSubImage1D","counts":{"deprecated":0,"unstable":0,"stable":0,"unmarked":3},"submodules":[]},{"name":"TexSubImage2D","counts":{"deprecated":0,"unstable":0,"stable":0,"unmarked":3},"submodules":[]},{"name":"TexSubImage3D","counts":{"deprecated":0,"unstable":0,"stable":0,"unmarked":3},"submodules":[]},{"name":"TransformFeedbackVaryings","counts":{"deprecated":0,"unstable":0,"stable":0,"unmarked":3},"submodules":[]},{"name":"Translated","counts":{"deprecated":0,"unstable":0,"stable":0,"unmarked":3},"submodules":[]},{"name":"Translatef","counts":{"deprecated":0,"unstable":0,"stable":0,"unmarked":3},"submodules":[]},{"name":"Uniform1f","counts":{"deprecated":0,"unstable":0,"stable":0,"unmarked":3},"submodules":[]},{"name":"Uniform1fv","counts":{"deprecated":0,"unstable":0,"stable":0,"unmarked":3},"submodules":[]},{"name":"Uniform1i","counts":{"deprecated":0,"unstable":0,"stable":0,"unmarked":3},"submodules":[]},{"name":"Uniform1iv","counts":{"deprecated":0,"unstable":0,"stable":0,"unmarked":3},"submodules":[]},{"name":"Uniform1ui","counts":{"deprecated":0,"unstable":0,"stable":0,"unmarked":3},"submodules":[]},{"name":"Uniform1uiv","counts":{"deprecated":0,"unstable":0,"stable":0,"unmarked":3},"submodules":[]},{"name":"Uniform2f","counts":{"deprecated":0,"unstable":0,"stable":0,"unmarked":3},"submodules":[]},{"name":"Uniform2fv","counts":{"deprecated":0,"unstable":0,"stable":0,"unmarked":3},"submodules":[]},{"name":"Uniform2i","counts":{"deprecated":0,"unstable":0,"stable":0,"unmarked":3},"submodules":[]},{"name":"Uniform2iv","counts":{"deprecated":0,"unstable":0,"stable":0,"unmarked":3},"submodules":[]},{"name":"Uniform2ui","counts":{"deprecated":0,"unstable":0,"stable":0,"unmarked":3},"submodules":[]},{"name":"Uniform2uiv","counts":{"deprecated":0,"unstable":0,"stable":0,"unmarked":3},"submodules":[]},{"name":"Uniform3f","counts":{"deprecated":0,"unstable":0,"stable":0,"unmarked":3},"submodules":[]},{"name":"Uniform3fv","counts":{"deprecated":0,"unstable":0,"stable":0,"unmarked":3},"submodules":[]},{"name":"Uniform3i","counts":{"deprecated":0,"unstable":0,"stable":0,"unmarked":3},"submodules":[]},{"name":"Uniform3iv","counts":{"deprecated":0,"unstable":0,"stable":0,"unmarked":3},"submodules":[]},{"name":"Uniform3ui","counts":{"deprecated":0,"unstable":0,"stable":0,"unmarked":3},"submodules":[]},{"name":"Uniform3uiv","counts":{"deprecated":0,"unstable":0,"stable":0,"unmarked":3},"submodules":[]},{"name":"Uniform4f","counts":{"deprecated":0,"unstable":0,"stable":0,"unmarked":3},"submodules":[]},{"name":"Uniform4fv","counts":{"deprecated":0,"unstable":0,"stable":0,"unmarked":3},"submodules":[]},{"name":"Uniform4i","counts":{"deprecated":0,"unstable":0,"stable":0,"unmarked":3},"submodules":[]},{"name":"Uniform4iv","counts":{"deprecated":0,"unstable":0,"stable":0,"unmarked":3},"submodules":[]},{"name":"Uniform4ui","counts":{"deprecated":0,"unstable":0,"stable":0,"unmarked":3},"submodules":[]},{"name":"Uniform4uiv","counts":{"deprecated":0,"unstable":0,"stable":0,"unmarked":3},"submodules":[]},{"name":"UniformMatrix2fv","counts":{"deprecated":0,"unstable":0,"stable":0,"unmarked":3},"submodules":[]},{"name":"UniformMatrix2x3fv","counts":{"deprecated":0,"unstable":0,"stable":0,"unmarked":3},"submodules":[]},{"name":"UniformMatrix2x4fv","counts":{"deprecated":0,"unstable":0,"stable":0,"unmarked":3},"submodules":[]},{"name":"UniformMatrix3fv","counts":{"deprecated":0,"unstable":0,"stable":0,"unmarked":3},"submodules":[]},{"name":"UniformMatrix3x2fv","counts":{"deprecated":0,"unstable":0,"stable":0,"unmarked":3},"submodules":[]},{"name":"UniformMatrix3x4fv","counts":{"deprecated":0,"unstable":0,"stable":0,"unmarked":3},"submodules":[]},{"name":"UniformMatrix4fv","counts":{"deprecated":0,"unstable":0,"stable":0,"unmarked":3},"submodules":[]},{"name":"UniformMatrix4x2fv","counts":{"deprecated":0,"unstable":0,"stable":0,"unmarked":3},"submodules":[]},{"name":"UniformMatrix4x3fv","counts":{"deprecated":0,"unstable":0,"stable":0,"unmarked":3},"submodules":[]},{"name":"UnmapBuffer","counts":{"deprecated":0,"unstable":0,"stable":0,"unmarked":3},"submodules":[]},{"name":"UseProgram","counts":{"deprecated":0,"unstable":0,"stable":0,"unmarked":3},"submodules":[]},{"name":"ValidateProgram","counts":{"deprecated":0,"unstable":0,"stable":0,"unmarked":3},"submodules":[]},{"name":"Vertex2d","counts":{"deprecated":0,"unstable":0,"stable":0,"unmarked":3},"submodules":[]},{"name":"Vertex2dv","counts":{"deprecated":0,"unstable":0,"stable":0,"unmarked":3},"submodules":[]},{"name":"Vertex2f","counts":{"deprecated":0,"unstable":0,"stable":0,"unmarked":3},"submodules":[]},{"name":"Vertex2fv","counts":{"deprecated":0,"unstable":0,"stable":0,"unmarked":3},"submodules":[]},{"name":"Vertex2i","counts":{"deprecated":0,"unstable":0,"stable":0,"unmarked":3},"submodules":[]},{"name":"Vertex2iv","counts":{"deprecated":0,"unstable":0,"stable":0,"unmarked":3},"submodules":[]},{"name":"Vertex2s","counts":{"deprecated":0,"unstable":0,"stable":0,"unmarked":3},"submodules":[]},{"name":"Vertex2sv","counts":{"deprecated":0,"unstable":0,"stable":0,"unmarked":3},"submodules":[]},{"name":"Vertex3d","counts":{"deprecated":0,"unstable":0,"stable":0,"unmarked":3},"submodules":[]},{"name":"Vertex3dv","counts":{"deprecated":0,"unstable":0,"stable":0,"unmarked":3},"submodules":[]},{"name":"Vertex3f","counts":{"deprecated":0,"unstable":0,"stable":0,"unmarked":3},"submodules":[]},{"name":"Vertex3fv","counts":{"deprecated":0,"unstable":0,"stable":0,"unmarked":3},"submodules":[]},{"name":"Vertex3i","counts":{"deprecated":0,"unstable":0,"stable":0,"unmarked":3},"submodules":[]},{"name":"Vertex3iv","counts":{"deprecated":0,"unstable":0,"stable":0,"unmarked":3},"submodules":[]},{"name":"Vertex3s","counts":{"deprecated":0,"unstable":0,"stable":0,"unmarked":3},"submodules":[]},{"name":"Vertex3sv","counts":{"deprecated":0,"unstable":0,"stable":0,"unmarked":3},"submodules":[]},{"name":"Vertex4d","counts":{"deprecated":0,"unstable":0,"stable":0,"unmarked":3},"submodules":[]},{"name":"Vertex4dv","counts":{"deprecated":0,"unstable":0,"stable":0,"unmarked":3},"submodules":[]},{"name":"Vertex4f","counts":{"deprecated":0,"unstable":0,"stable":0,"unmarked":3},"submodules":[]},{"name":"Vertex4fv","counts":{"deprecated":0,"unstable":0,"stable":0,"unmarked":3},"submodules":[]},{"name":"Vertex4i","counts":{"deprecated":0,"unstable":0,"stable":0,"unmarked":3},"submodules":[]},{"name":"Vertex4iv","counts":{"deprecated":0,"unstable":0,"stable":0,"unmarked":3},"submodules":[]},{"name":"Vertex4s","counts":{"deprecated":0,"unstable":0,"stable":0,"unmarked":3},"submodules":[]},{"name":"Vertex4sv","counts":{"deprecated":0,"unstable":0,"stable":0,"unmarked":3},"submodules":[]},{"name":"VertexAttrib1d","counts":{"deprecated":0,"unstable":0,"stable":0,"unmarked":3},"submodules":[]},{"name":"VertexAttrib1dv","counts":{"deprecated":0,"unstable":0,"stable":0,"unmarked":3},"submodules":[]},{"name":"VertexAttrib1f","counts":{"deprecated":0,"unstable":0,"stable":0,"unmarked":3},"submodules":[]},{"name":"VertexAttrib1fv","counts":{"deprecated":0,"unstable":0,"stable":0,"unmarked":3},"submodules":[]},{"name":"VertexAttrib1s","counts":{"deprecated":0,"unstable":0,"stable":0,"unmarked":3},"submodules":[]},{"name":"VertexAttrib1sv","counts":{"deprecated":0,"unstable":0,"stable":0,"unmarked":3},"submodules":[]},{"name":"VertexAttrib2d","counts":{"deprecated":0,"unstable":0,"stable":0,"unmarked":3},"submodules":[]},{"name":"VertexAttrib2dv","counts":{"deprecated":0,"unstable":0,"stable":0,"unmarked":3},"submodules":[]},{"name":"VertexAttrib2f","counts":{"deprecated":0,"unstable":0,"stable":0,"unmarked":3},"submodules":[]},{"name":"VertexAttrib2fv","counts":{"deprecated":0,"unstable":0,"stable":0,"unmarked":3},"submodules":[]},{"name":"VertexAttrib2s","counts":{"deprecated":0,"unstable":0,"stable":0,"unmarked":3},"submodules":[]},{"name":"VertexAttrib2sv","counts":{"deprecated":0,"unstable":0,"stable":0,"unmarked":3},"submodules":[]},{"name":"VertexAttrib3d","counts":{"deprecated":0,"unstable":0,"stable":0,"unmarked":3},"submodules":[]},{"name":"VertexAttrib3dv","counts":{"deprecated":0,"unstable":0,"stable":0,"unmarked":3},"submodules":[]},{"name":"VertexAttrib3f","counts":{"deprecated":0,"unstable":0,"stable":0,"unmarked":3},"submodules":[]},{"name":"VertexAttrib3fv","counts":{"deprecated":0,"unstable":0,"stable":0,"unmarked":3},"submodules":[]},{"name":"VertexAttrib3s","counts":{"deprecated":0,"unstable":0,"stable":0,"unmarked":3},"submodules":[]},{"name":"VertexAttrib3sv","counts":{"deprecated":0,"unstable":0,"stable":0,"unmarked":3},"submodules":[]},{"name":"VertexAttrib4Nbv","counts":{"deprecated":0,"unstable":0,"stable":0,"unmarked":3},"submodules":[]},{"name":"VertexAttrib4Niv","counts":{"deprecated":0,"unstable":0,"stable":0,"unmarked":3},"submodules":[]},{"name":"VertexAttrib4Nsv","counts":{"deprecated":0,"unstable":0,"stable":0,"unmarked":3},"submodules":[]},{"name":"VertexAttrib4Nub","counts":{"deprecated":0,"unstable":0,"stable":0,"unmarked":3},"submodules":[]},{"name":"VertexAttrib4Nubv","counts":{"deprecated":0,"unstable":0,"stable":0,"unmarked":3},"submodules":[]},{"name":"VertexAttrib4Nuiv","counts":{"deprecated":0,"unstable":0,"stable":0,"unmarked":3},"submodules":[]},{"name":"VertexAttrib4Nusv","counts":{"deprecated":0,"unstable":0,"stable":0,"unmarked":3},"submodules":[]},{"name":"VertexAttrib4bv","counts":{"deprecated":0,"unstable":0,"stable":0,"unmarked":3},"submodules":[]},{"name":"VertexAttrib4d","counts":{"deprecated":0,"unstable":0,"stable":0,"unmarked":3},"submodules":[]},{"name":"VertexAttrib4dv","counts":{"deprecated":0,"unstable":0,"stable":0,"unmarked":3},"submodules":[]},{"name":"VertexAttrib4f","counts":{"deprecated":0,"unstable":0,"stable":0,"unmarked":3},"submodules":[]},{"name":"VertexAttrib4fv","counts":{"deprecated":0,"unstable":0,"stable":0,"unmarked":3},"submodules":[]},{"name":"VertexAttrib4iv","counts":{"deprecated":0,"unstable":0,"stable":0,"unmarked":3},"submodules":[]},{"name":"VertexAttrib4s","counts":{"deprecated":0,"unstable":0,"stable":0,"unmarked":3},"submodules":[]},{"name":"VertexAttrib4sv","counts":{"deprecated":0,"unstable":0,"stable":0,"unmarked":3},"submodules":[]},{"name":"VertexAttrib4ubv","counts":{"deprecated":0,"unstable":0,"stable":0,"unmarked":3},"submodules":[]},{"name":"VertexAttrib4uiv","counts":{"deprecated":0,"unstable":0,"stable":0,"unmarked":3},"submodules":[]},{"name":"VertexAttrib4usv","counts":{"deprecated":0,"unstable":0,"stable":0,"unmarked":3},"submodules":[]},{"name":"VertexAttribI1i","counts":{"deprecated":0,"unstable":0,"stable":0,"unmarked":3},"submodules":[]},{"name":"VertexAttribI1iv","counts":{"deprecated":0,"unstable":0,"stable":0,"unmarked":3},"submodules":[]},{"name":"VertexAttribI1ui","counts":{"deprecated":0,"unstable":0,"stable":0,"unmarked":3},"submodules":[]},{"name":"VertexAttribI1uiv","counts":{"deprecated":0,"unstable":0,"stable":0,"unmarked":3},"submodules":[]},{"name":"VertexAttribI2i","counts":{"deprecated":0,"unstable":0,"stable":0,"unmarked":3},"submodules":[]},{"name":"VertexAttribI2iv","counts":{"deprecated":0,"unstable":0,"stable":0,"unmarked":3},"submodules":[]},{"name":"VertexAttribI2ui","counts":{"deprecated":0,"unstable":0,"stable":0,"unmarked":3},"submodules":[]},{"name":"VertexAttribI2uiv","counts":{"deprecated":0,"unstable":0,"stable":0,"unmarked":3},"submodules":[]},{"name":"VertexAttribI3i","counts":{"deprecated":0,"unstable":0,"stable":0,"unmarked":3},"submodules":[]},{"name":"VertexAttribI3iv","counts":{"deprecated":0,"unstable":0,"stable":0,"unmarked":3},"submodules":[]},{"name":"VertexAttribI3ui","counts":{"deprecated":0,"unstable":0,"stable":0,"unmarked":3},"submodules":[]},{"name":"VertexAttribI3uiv","counts":{"deprecated":0,"unstable":0,"stable":0,"unmarked":3},"submodules":[]},{"name":"VertexAttribI4bv","counts":{"deprecated":0,"unstable":0,"stable":0,"unmarked":3},"submodules":[]},{"name":"VertexAttribI4i","counts":{"deprecated":0,"unstable":0,"stable":0,"unmarked":3},"submodules":[]},{"name":"VertexAttribI4iv","counts":{"deprecated":0,"unstable":0,"stable":0,"unmarked":3},"submodules":[]},{"name":"VertexAttribI4sv","counts":{"deprecated":0,"unstable":0,"stable":0,"unmarked":3},"submodules":[]},{"name":"VertexAttribI4ubv","counts":{"deprecated":0,"unstable":0,"stable":0,"unmarked":3},"submodules":[]},{"name":"VertexAttribI4ui","counts":{"deprecated":0,"unstable":0,"stable":0,"unmarked":3},"submodules":[]},{"name":"VertexAttribI4uiv","counts":{"deprecated":0,"unstable":0,"stable":0,"unmarked":3},"submodules":[]},{"name":"VertexAttribI4usv","counts":{"deprecated":0,"unstable":0,"stable":0,"unmarked":3},"submodules":[]},{"name":"VertexAttribIPointer","counts":{"deprecated":0,"unstable":0,"stable":0,"unmarked":3},"submodules":[]},{"name":"VertexAttribPointer","counts":{"deprecated":0,"unstable":0,"stable":0,"unmarked":3},"submodules":[]},{"name":"VertexPointer","counts":{"deprecated":0,"unstable":0,"stable":0,"unmarked":3},"submodules":[]},{"name":"Viewport","counts":{"deprecated":0,"unstable":0,"stable":0,"unmarked":3},"submodules":[]},{"name":"WindowPos2d","counts":{"deprecated":0,"unstable":0,"stable":0,"unmarked":3},"submodules":[]},{"name":"WindowPos2dv","counts":{"deprecated":0,"unstable":0,"stable":0,"unmarked":3},"submodules":[]},{"name":"WindowPos2f","counts":{"deprecated":0,"unstable":0,"stable":0,"unmarked":3},"submodules":[]},{"name":"WindowPos2fv","counts":{"deprecated":0,"unstable":0,"stable":0,"unmarked":3},"submodules":[]},{"name":"WindowPos2i","counts":{"deprecated":0,"unstable":0,"stable":0,"unmarked":3},"submodules":[]},{"name":"WindowPos2iv","counts":{"deprecated":0,"unstable":0,"stable":0,"unmarked":3},"submodules":[]},{"name":"WindowPos2s","counts":{"deprecated":0,"unstable":0,"stable":0,"unmarked":3},"submodules":[]},{"name":"WindowPos2sv","counts":{"deprecated":0,"unstable":0,"stable":0,"unmarked":3},"submodules":[]},{"name":"WindowPos3d","counts":{"deprecated":0,"unstable":0,"stable":0,"unmarked":3},"submodules":[]},{"name":"WindowPos3dv","counts":{"deprecated":0,"unstable":0,"stable":0,"unmarked":3},"submodules":[]},{"name":"WindowPos3f","counts":{"deprecated":0,"unstable":0,"stable":0,"unmarked":3},"submodules":[]},{"name":"WindowPos3fv","counts":{"deprecated":0,"unstable":0,"stable":0,"unmarked":3},"submodules":[]},{"name":"WindowPos3i","counts":{"deprecated":0,"unstable":0,"stable":0,"unmarked":3},"submodules":[]},{"name":"WindowPos3iv","counts":{"deprecated":0,"unstable":0,"stable":0,"unmarked":3},"submodules":[]},{"name":"WindowPos3s","counts":{"deprecated":0,"unstable":0,"stable":0,"unmarked":3},"submodules":[]},{"name":"WindowPos3sv","counts":{"deprecated":0,"unstable":0,"stable":0,"unmarked":3},"submodules":[]},{"name":"types","counts":{"deprecated":0,"unstable":0,"stable":0,"unmarked":42},"submodules":[]}]}]}